{
    "chapter": "第二十章 数据的分析",
    "sections": [
        {
            "sectionTitle": "16.1 二次根式",
            "subsections": [
                {
                    "subsectionTitle": "求二次根式的值",
                    "knowledgePoints": []
                },
                {
                    "subsectionTitle": "求二次根式中的参数",
                    "knowledgePoints": []
                },
                {
                    "subsectionTitle": "二次根式有意义的条件",
                    "knowledgePoints": []
                },
                {
                    "subsectionTitle": "利用二次根式的性质化简",
                    "knowledgePoints": []
                },
                {
                    "subsectionTitle": "复合二次根式的化简",
                    "knowledgePoints": []
                }
            ],
            "knowledgePoints": []
        },
        {
            "sectionTitle": "16.2 二次根式的乘除",
            "subsections": [
                {
                    "subsectionTitle": "二次根式的乘法",
                    "knowledgePoints": []
                },
                {
                    "subsectionTitle": "二次根式的除法",
                    "knowledgePoints": []
                },
                {
                    "subsectionTitle": "二次根式的乘除混合运算",
                    "knowledgePoints": []
                },
                {
                    "subsectionTitle": "最简二次根式的判断",
                    "knowledgePoints": []
                },
                {
                    "subsectionTitle": "化为最简二次根式",
                    "knowledgePoints": []
                },
                {
                    "subsectionTitle": "已知最简二次根式求参数",
                    "knowledgePoints": []
                }
            ],
            "knowledgePoints": []
        },
        {
            "sectionTitle": "16.3 二次根式的加减",
            "subsections": [
                {
                    "subsectionTitle": "同类二次根式",
                    "knowledgePoints": []
                },
                {
                    "subsectionTitle": "二次根式的加减运算",
                    "knowledgePoints": []
                },
                {
                    "subsectionTitle": "二次根式的混合运算",
                    "knowledgePoints": []
                },
                {
                    "subsectionTitle": "分母有理化",
                    "knowledgePoints": []
                },
                {
                    "subsectionTitle": "已知字母的值，化简求值",
                    "knowledgePoints": []
                },
                {
                    "subsectionTitle": "已知条件式，化简求值",
                    "knowledgePoints": []
                },
                {
                    "subsectionTitle": "比较二次根式的大小",
                    "knowledgePoints": []
                },
                {
                    "subsectionTitle": "二次根式的应用",
                    "knowledgePoints": []
                }
            ],
            "knowledgePoints": []
        },
        {
            "sectionTitle": "17.1 勾股定理",
            "subsections": [
                {
                    "subsectionTitle": "用勾股定理解三角形",
                    "knowledgePoints": []
                },
                {
                    "subsectionTitle": "已知两点坐标求两点距离",
                    "knowledgePoints": []
                },
                {
                    "subsectionTitle": "勾股树（数）问题",
                    "knowledgePoints": []
                },
                {
                    "subsectionTitle": "以直角三角形三边为边长的图形面积",
                    "knowledgePoints": []
                },
                {
                    "subsectionTitle": "勾股定理与网格问题",
                    "knowledgePoints": []
                },
                {
                    "subsectionTitle": "勾股定理与折叠问题",
                    "knowledgePoints": []
                },
                {
                    "subsectionTitle": "利用勾股定理求两条线段的平方和（差）",
                    "knowledgePoints": []
                },
                {
                    "subsectionTitle": "利用勾股定理证明线段平方关系",
                    "knowledgePoints": []
                },
                {
                    "subsectionTitle": "勾股定理的证明方法",
                    "knowledgePoints": []
                },
                {
                    "subsectionTitle": "以弦图为背景的计算题",
                    "knowledgePoints": []
                },
                {
                    "subsectionTitle": "用勾股定理构造图形解决问题",
                    "knowledgePoints": []
                },
                {
                    "subsectionTitle": "勾股定理与无理数",
                    "knowledgePoints": []
                },
                {
                    "subsectionTitle": "求梯子滑落高度(勾股定理的应用)",
                    "knowledgePoints": []
                },
                {
                    "subsectionTitle": "求旗杆高度(勾股定理的应用)",
                    "knowledgePoints": []
                },
                {
                    "subsectionTitle": "求小鸟飞行距离(勾股定理的应用)",
                    "knowledgePoints": []
                },
                {
                    "subsectionTitle": "求大树折断前的高度(勾股定理的应用)",
                    "knowledgePoints": []
                },
                {
                    "subsectionTitle": "解决水杯中筷子问题(勾股定理的应用)",
                    "knowledgePoints": []
                },
                {
                    "subsectionTitle": "解决航海问题(勾股定理的应用)",
                    "knowledgePoints": []
                },
                {
                    "subsectionTitle": "求河宽(勾股定理的应用)",
                    "knowledgePoints": []
                },
                {
                    "subsectionTitle": "求台阶上地毯长度(勾股定理的应用)",
                    "knowledgePoints": []
                },
                {
                    "subsectionTitle": "判断汽车是否超速(勾股定理的应用)",
                    "knowledgePoints": []
                },
                {
                    "subsectionTitle": "判断是否受台风影响(勾股定理的应用)",
                    "knowledgePoints": []
                },
                {
                    "subsectionTitle": "选址使到两地距离相等(勾股定理的应用)",
                    "knowledgePoints": []
                },
                {
                    "subsectionTitle": "求最短路径(勾股定理的应用)",
                    "knowledgePoints": []
                }
            ],
            "knowledgePoints": []
        },
        {
            "sectionTitle": "17.2 勾股定理的逆定理",
            "subsections": [
                {
                    "subsectionTitle": "判断三边能否构成直角三角形",
                    "knowledgePoints": []
                },
                {
                    "subsectionTitle": "图形上与已知两点构成直角三角形的点",
                    "knowledgePoints": []
                },
                {
                    "subsectionTitle": "在网格中判断直角三角形",
                    "knowledgePoints": []
                },
                {
                    "subsectionTitle": "利用勾股定理的逆定理求解",
                    "knowledgePoints": []
                },
                {
                    "subsectionTitle": "勾股定理逆定理的实际应用",
                    "knowledgePoints": []
                },
                {
                    "subsectionTitle": "勾股定理逆定理的拓展问题",
                    "knowledgePoints": []
                }
            ],
            "knowledgePoints": []
        },
        {
            "sectionTitle": "18.1 平行四边形",
            "subsections": [
                {
                    "subsectionTitle": "18.1.1 平行四边形的性质",
                    "knowledgePoints": [
                        "利用平行四边形的性质求解",
                        "利用平行四边形的性质证明",
                        "平行四边形性质的其他应用"
                    ]
                },
                {
                    "subsectionTitle": "18.1.2 平行四边形的判定",
                    "knowledgePoints": [
                        "判断能否构成平行四边形",
                        "添一个条件成为平行四边形",
                        "数图形中平行四边形的个数",
                        "求与已知三点组成平行四边形的点的个数",
                        "证明四边形是平行四边形",
                        "全等三角形拼平行四边形问题",
                        "利用平行四边形的判定与性质求解",
                        "利用平行四边形性质和判定证明",
                        "平行四边形性质和判定的应用",
                        "与三角形中位线有关的求解问题",
                        "与三角形中位线有关的证明",
                        "三角形中位线的实际应用"
                    ]
                }
            ],
            "knowledgePoints": []
        },
        {
            "sectionTitle": "18.2 特殊的平行四边形",
            "subsections": [
                {
                    "subsectionTitle": "18.2.1 矩形",
                    "knowledgePoints": [
                        "矩形性质理解",
                        "利用矩形的性质求角度",
                        "根据矩形的性质求线段长",
                        "根据矩形的性质求面积",
                        "利用矩形的性质证明",
                        " 求矩形在坐标系中的坐标",
                        "矩形与折叠问题",
                        "斜边的中线等于斜边的一半",
                        "矩形的判定定理理解",
                        "添一条件使四边形是矩形",
                        "证明四边形是矩形",
                        "根据矩形的性质与判定求角度",
                        "根据矩形的性质与判定求线段长",
                        "根据矩形的性质与判定求面积"
                    ]
                },
                {
                    "subsectionTitle": "18.2.2 菱形",
                    "knowledgePoints": [
                        "利用菱形的性质求角度",
                        "利用菱形的性质求线段长",
                        "利用菱形的性质求面积",
                        "利用菱形的性质证明",
                        "添一个条件使四边形是菱形",
                        "证明四边形是菱形",
                        "根据菱形的性质与判定求角度",
                        "根据菱形的性质与判定求线段长",
                        "根据菱形的性质与判定求面积"
                    ]
                },
                {
                    "subsectionTitle": "18.2.3 正方形",
                    "knowledgePoints": [
                        "正方形性质理解",
                        "根据正方形的性质求角度",
                        "根据正方形的性质求线段长",
                        "根据正方形的性质求面积",
                        "正方形折叠问题",
                        "求正方形重叠部分面积",
                        "根据正方形的性质证明",
                        "正方形的判定定理理解",
                        "添一个条件使四边形是正方形",
                        "证明四边形是正方形",
                        "根据正方形的性质与判定求角度",
                        "根据正方形的性质与判定求线段长",
                        "根据正方形的性质与判定求面积",
                        "根据正方形的性质与判定证明",
                        "中点四边形",
                        "利用（特殊)平行四边形的对称性求阴影面积",
                        "（特殊）平行四边形的动点问题",
                        "四边形中的线段最值问题",
                        "四边形其他综合问题"
                    ]
                }
            ],
            "knowledgePoints": []
        },
        {
            "sectionTitle": "19.1 函数",
            "subsections": [
                {
                    "subsectionTitle": "19.1.1 变量与函数",
                    "knowledgePoints": [
                        "函数的概念",
                        "函数解析式",
                        "求自变量的取值范围",
                        "求自变量的值或函数值",
                        "用表格表示变量间的关系",
                        "用关系式表示变量间的关系",
                        "用图象表示变量间的关系"
                    ]
                },
                {
                    "subsectionTitle": "19.1.2 函数的图象",
                    "knowledgePoints": [
                        "函数图象识别",
                        "从函数的图象获取信息",
                        "用描点法画函数图象",
                        "动点问题的函数图象",
                        "函数的三种表示方法"
                    ]
                }
            ],
            "knowledgePoints": []
        },
        {
            "sectionTitle": "19.2 一次函数",
            "subsections": [
                {
                    "subsectionTitle": "19.2.1 正比例函数",
                    "knowledgePoints": [
                        "正比例函数的定义",
                        "正比例函数的图象",
                        "正比例函数的性质"
                    ]
                },
                {
                    "subsectionTitle": "19.2.2 一次函数",
                    "knowledgePoints": [
                        "识别一次函数",
                        "根据一次函数的定义求参数",
                        "求一次函数自变量或函数值",
                        "列一次函数解析式并求值",
                        "判断一次函数的图象",
                        "根据一次函数解析式判断其经过的象限",
                        "已知函数经过的象限求参数范围",
                        "一次函数图象与坐标轴的交点问题",
                        "画一次函数图象",
                        "一次函数图象平移问题",
                        "判断一次函数的增减性",
                        "根据一次函数增减性求参数",
                        "根据一次函数的增减性判断自变量的变化情况",
                        "比较一次函数值的大小",
                        "一次函数的规律探究问题",
                        "求一次函数解析式",
                        "一次函数图象与对称问题",
                        "一次函数图象与旋转问题"
                    ]
                },
                {
                    "subsectionTitle": "19.2.3 一次函数与方程、不等式",
                    "knowledgePoints": [
                        "已知直线与坐标轴交点求方程的解",
                        "由一元一次方程的解判断直线与x轴的交点",
                        "利用图象法解一元一次方程",
                        "由直线与坐标轴的交点求不等式的解集",
                        "根据两条直线的交点求不等式的解集",
                        "两直线的交点与二元一次方程组的解",
                        "图象法解二元一次方程组",
                        "求直线围成的图形面积"
                    ]
                }
            ],
            "knowledgePoints": []
        },
        {
            "sectionTitle": "19.3 课题学习  选择方案",
            "subsections": [
                {
                    "subsectionTitle": "分配方案问题(一次函数的实际应用)",
                    "knowledgePoints": []
                },
                {
                    "subsectionTitle": "最大利润问题(一次函数的实际应用)",
                    "knowledgePoints": []
                },
                {
                    "subsectionTitle": "行程问题(一次函数的实际应用)",
                    "knowledgePoints": []
                },
                {
                    "subsectionTitle": "一次函数与几何综合",
                    "knowledgePoints": []
                },
                {
                    "subsectionTitle": "其他问题(一次函数的实际应用)",
                    "knowledgePoints": []
                },
                {
                    "subsectionTitle": "梯度计价问题",
                    "knowledgePoints": []
                }
            ],
            "knowledgePoints": []
        },
        {
            "sectionTitle": "20.1 数据的集中趋势",
            "subsections": [
                {
                    "subsectionTitle": "20.1.1 平均数",
                    "knowledgePoints": [
                        "求一组数据的平均数",
                        "已知 平均数求未知数据的值",
                        " 利用已知的平均数求相关数据的平均数",
                        "利用平均数做决策",
                        "求加权平均数",
                        " 利用加权平均数求未知数据的值",
                        "运用加权平均数做决策",
                        "出错情况下的平均数问题",
                        "用计算器求平均数"
                    ]
                },
                {
                    "subsectionTitle": "20.1.2 中位数和众数",
                    "knowledgePoints": [
                        "求中位数",
                        " 利用中位数求未知数据的值",
                        "运用中位数做决策",
                        "求众数",
                        " 利用众数求未知数据的值",
                        "运用众数做决策"
                    ]
                }
            ],
            "knowledgePoints": []
        },
        {
            "sectionTitle": "20.2 数据的波动程度",
            "subsections": [
                {
                    "subsectionTitle": "求方差",
                    "knowledgePoints": []
                },
                {
                    "subsectionTitle": " 利用方差求未知数据的值",
                    "knowledgePoints": []
                },
                {
                    "subsectionTitle": "根据方差判断稳定性",
                    "knowledgePoints": []
                },
                {
                    "subsectionTitle": "运用方差做决策",
                    "knowledgePoints": []
                },
                {
                    "subsectionTitle": "求极差",
                    "knowledgePoints": []
                },
                {
                    "subsectionTitle": " 已知极差求未知数据",
                    "knowledgePoints": []
                },
                {
                    "subsectionTitle": "标准差",
                    "knowledgePoints": []
                },
                {
                    "subsectionTitle": "平均差",
                    "knowledgePoints": []
                },
                {
                    "subsectionTitle": "用计算器求方差",
                    "knowledgePoints": []
                }
            ],
            "knowledgePoints": []
        },
        {
            "sectionTitle": "20.3 课题学习  体质健康测试中的数据分析",
            "subsections": [],
            "knowledgePoints": []
        }
    ]
}